nlweb_azure_vectordb/__init__.py
nlweb_azure_vectordb/azure_search_client.py
nlweb_azure_vectordb/azure_search_writer.py
nlweb_azure_vectordb-0.5.6.dist-info/METADATA
nlweb_azure_vectordb-0.5.6.dist-info/WHEEL
nlweb_azure_vectordb-0.5.6.dist-info/top_level.txt
nlweb_azure_vectordb-0.5.6.dist-info/RECORD
