Metadata-Version: 2.4
Name: nlweb-azure-vectordb
Version: 0.5.6
Summary: Azure vector database provider for NLWeb - Azure AI Search client
Author: Microsoft Corporation
License: MIT
Project-URL: Homepage, https://github.com/microsoft/NLWeb_Core
Project-URL: Repository, https://github.com/microsoft/NLWeb_Core
Project-URL: Issues, https://github.com/microsoft/NLWeb_Core/issues
Classifier: Development Status :: 4 - Beta
Classifier: Intended Audience :: Developers
Classifier: License :: OSI Approved :: MIT License
Classifier: Programming Language :: Python :: 3
Classifier: Programming Language :: Python :: 3.9
Classifier: Programming Language :: Python :: 3.10
Classifier: Programming Language :: Python :: 3.11
Classifier: Programming Language :: Python :: 3.12
Requires-Python: >=3.9
Requires-Dist: nlweb-core>=0.5.5
Requires-Dist: azure-core
Requires-Dist: azure-search-documents>=11.4.0
Requires-Dist: azure-identity>=1.12.0
Provides-Extra: dev
Requires-Dist: pytest>=7.0; extra == "dev"
Requires-Dist: pytest-asyncio>=0.21.0; extra == "dev"
